LICENSE
README.md
pyproject.toml
setup.cfg
setup.py
src/confoid/__init__.py
src/confoid/base.py
src/confoid/constants.py
src/confoid/exceptions.py
src/confoid/validator.py
src/confoid.egg-info/PKG-INFO
src/confoid.egg-info/SOURCES.txt
src/confoid.egg-info/dependency_links.txt
src/confoid.egg-info/requires.txt
src/confoid.egg-info/top_level.txt
src/confoid/loaders/__init__.py
src/confoid/loaders/base.py
src/confoid/loaders/yaml_loader.py